{
  "D_cov_stats": {
    "ci_95_hi": 2.8931498070173958,
    "ci_95_lo": 2.193484197851732,
    "mean": 2.5308549688958153,
    "std": 0.44410560814654637
  },
  "D_occ_stats": {
    "ci_95_hi": 0.1230554925305152,
    "ci_95_lo": 0.06964653988526615,
    "mean": 0.09636203169622418,
    "std": 0.033684058836020984
  },
  "D_spec_stats": {
    "ci_95_hi": 1.0369921366796846e+16,
    "ci_95_lo": -2.0739842733593684e+16,
    "mean": -1.036992136679684e+16,
    "std": NaN
  },
  "alpha": 0.015,
  "elapsed_seconds": 24.026144900009967,
  "n_seeds": 5,
  "runs": [
    {
      "D_cov": 2.1221107504900703,
      "D_occ": 0.0607861158522784,
      "D_spec": 1.0369921366796846e+16,
      "n_samples": 100,
      "seed": 1
    },
    {
      "D_cov": 2.7247938920023844,
      "D_occ": 0.1313850246640801,
      "D_spec": -2.0739842733593684e+16,
      "n_samples": 100,
      "seed": 2
    },
    {
      "D_cov": 3.2062814641981747,
      "D_occ": 0.1312748697807451,
      "D_spec": Infinity,
      "n_samples": 100,
      "seed": 3
    },
    {
      "D_cov": 2.405301533972282,
      "D_occ": 0.06829631953775668,
      "D_spec": Infinity,
      "n_samples": 100,
      "seed": 4
    },
    {
      "D_cov": 2.1957872038161677,
      "D_occ": 0.09006782864626062,
      "D_spec": -2.0739842733593684e+16,
      "n_samples": 100,
      "seed": 5
    }
  ],
  "seed_list": [
    1,
    2,
    3,
    4,
    5
  ]
}