{
  "calibration": {
    "cross_eta": 2.0715793129698226e-08,
    "initial_target_radius": 0.00021165345794842206,
    "pulse_steps_reference": 100,
    "response_fraction_per_memory": 0.03,
    "source_center_offset": [
      1.0,
      0.0,
      0.0
    ]
  },
  "checkpoint": "data/processed/reference_states/scalar_Aatt35_N100M_d3_d10_seed1_2026-07-16/scalar_Aatt35_d3_seed1_N100000000.npz",
  "checkpoint_age_memory_times_alpha_n": 1000000.0,
  "checkpoint_update_index": 100000000,
  "created_utc": "2026-07-20T09:26:56.501328+00:00",
  "description": "One-way dynamic scalar-source continuation with paired controls.",
  "formation_seed": 1,
  "gate": {
    "dynamic_angular_orientation_coherence_median": 0.09739986069336154,
    "dynamic_dephasing_memory_times_median": 0.2,
    "dynamic_source_readout_pass": false,
    "dynamic_tangential_fraction_median": 0.8769608045988309,
    "free_angular_orientation_coherence_median": 0.09739894735150204,
    "interaction_readout_pass": false,
    "launch_specific_source_displacement_radii_median": 10.94402932384184,
    "launch_specific_target_readout_pass": false,
    "launch_specific_target_response_radii_median": 0.0002332278525209654,
    "relational_phase_candidate_pass": false,
    "source_max_radius_factor_median": 1.5904457119683941,
    "source_shape_bounded_coherent_pass": false,
    "source_shape_bounded_pass": true,
    "source_shape_coherent_pass": false,
    "source_shape_spectrum_distance_median": 8.881784197001252e-16,
    "source_stationarity_radius_drift_median": 0.009950659256005467,
    "source_stationarity_spectrum_drift_median": 0.006319263485189575,
    "stationary_source_shape_pass": true,
    "target_shape_bounded_coherent_pass": true,
    "target_shape_bounded_pass": true,
    "target_shape_coherent_pass": true,
    "zero_cross_identity_pass": true,
    "zero_cross_max_abs_error": 0.0
  },
  "git_revision": "e3f053bc69e130fc081d6d69edfa24de5e52f28c",
  "git_status": "",
  "launch": {
    "source_launch_axis": 1,
    "source_launch_delay_memory_times": 50.0,
    "source_launch_memory_times": 10.0,
    "source_launch_sigma_rep": 0.1
  },
  "memory_time_updates_approx": 100.0,
  "memory_time_updates_exact_efold": 99.49916247342216,
  "model": {
    "alpha": 0.01,
    "dim": 3,
    "epsilon": 0.0001,
    "eta": 0.15
  },
  "parameters": {
    "continuation_seeds": [
      1,
      2,
      3,
      4,
      5
    ],
    "max_ac_memory_times": 50.0,
    "response_fraction_per_memory": 0.03,
    "sample_every": 20,
    "separation_sigma_rep": 1.0,
    "source_launch_axis": 1,
    "source_launch_delay_memory_times": 50.0,
    "source_launch_memory_times": 10.0,
    "source_launch_sigma_rep": 0.1,
    "steps": 20000
  },
  "rows": [
    {
      "continuation_seed": 1,
      "dynamic_minus_free_final_radii": 0.13893224363899573,
      "dynamic_minus_frozen_final_radii": 0.00022234594365124177,
      "dynamic_separation_final": 0.9997395951705528,
      "dynamic_separation_initial": 0.9999999999999974,
      "dynamic_separation_ratio": 0.9997395951705553,
      "launch_specific_source_displacement_radii": 10.94402932384184,
      "launch_specific_target_response_radii": 0.0002332278525209654,
      "max_active_target_radius_disturbance": 0.0001632130587666536,
      "max_eta_zero_radius_disturbance": 8.091598223449683,
      "max_launch_specific_source_radius_effect": 0.566778370347842,
      "max_source_radius_disturbance": 0.5686889196422731,
      "orbital_metrics": {
        "dynamic_source": {
          "angular_momentum_norm_median": 8.47413263787043e-07,
          "angular_orientation_coherence": 0.09739986069336154,
          "angular_speed_median_per_memory_time": 8.474371453765903e-05,
          "dephasing_censored": false,
          "dephasing_memory_times": 0.2,
          "tangential_fraction_median": 0.8779539242129231
        },
        "eta_zero_dynamic": {
          "angular_momentum_norm_median": 8.771079299810268e-06,
          "angular_orientation_coherence": 0.07067673412597186,
          "angular_speed_median_per_memory_time": 0.0008756586054293626,
          "dephasing_censored": false,
          "dephasing_memory_times": 1.2000000000000002,
          "tangential_fraction_median": 0.8805127967262389
        },
        "free": {
          "angular_momentum_norm_median": 8.474298580563023e-07,
          "angular_orientation_coherence": 0.09739894735150204,
          "angular_speed_median_per_memory_time": 8.474205962389487e-05,
          "dephasing_censored": false,
          "dephasing_memory_times": 0.2,
          "tangential_fraction_median": 0.8777227763123923
        },
        "frozen_source": {
          "angular_momentum_norm_median": 5.849849310862752e-07,
          "angular_orientation_coherence": 0.026661588494799885,
          "angular_speed_median_per_memory_time": 5.850627096123193e-05,
          "dephasing_censored": false,
          "dephasing_memory_times": 0.2,
          "tangential_fraction_median": 0.8649222851860998
        }
      },
      "source_displacement_radii": 9.938651549262278,
      "source_launch_axis": 1,
      "source_launch_sigma_rep": 0.1,
      "source_launch_start_step": 5000,
      "source_launch_steps": 1000,
      "source_shape_response": {
        "max_radius_factor": 1.5685898646977199,
        "radius_factor_limit": 2.0,
        "shape_bounded_coherent_pass": false,
        "shape_bounded_pass": true,
        "shape_coherent_pass": false,
        "shape_spectrum_distance_median": 8.881784197001252e-16,
        "shape_spectrum_distance_q95": 0.2541250688575186,
        "spectrum_median_limit": 0.1,
        "spectrum_q95_limit": 0.25
      },
      "source_stationarity": {
        "radius_coefficient_of_variation": 0.029966533080940227,
        "radius_cv_limit": 0.15,
        "radius_drift_limit": 0.1,
        "radius_relative_drift": 0.009950659256005467,
        "shape_spectrum_total_variation": 0.005040840316974438,
        "spectrum_drift_limit": 0.1,
        "stationary_shape_pass": true
      },
      "target_shape_response": {
        "max_radius_factor": 1.0000003744080352,
        "radius_factor_limit": 2.0,
        "shape_bounded_coherent_pass": true,
        "shape_bounded_pass": true,
        "shape_coherent_pass": true,
        "shape_spectrum_distance_median": 1.2394987905506305e-07,
        "shape_spectrum_distance_q95": 2.6361903908422857e-07,
        "spectrum_median_limit": 0.1,
        "spectrum_q95_limit": 0.25
      }
    },
    {
      "continuation_seed": 2,
      "dynamic_minus_free_final_radii": 0.13894048539590093,
      "dynamic_minus_frozen_final_radii": 0.00024076842905759334,
      "dynamic_separation_final": 1.0003616818231353,
      "dynamic_separation_initial": 0.9999999999999974,
      "dynamic_separation_ratio": 1.000361681823138,
      "launch_specific_source_displacement_radii": 10.944029308778818,
      "launch_specific_target_response_radii": 0.00023322933891100148,
      "max_active_target_radius_disturbance": 0.00015104098469476135,
      "max_eta_zero_radius_disturbance": 8.216042914183468,
      "max_launch_specific_source_radius_effect": 0.5397496483621701,
      "max_source_radius_disturbance": 0.5376539499753117,
      "orbital_metrics": {
        "dynamic_source": {
          "angular_momentum_norm_median": 8.684353023259305e-07,
          "angular_orientation_coherence": 0.097629082272215,
          "angular_speed_median_per_memory_time": 8.684505834394102e-05,
          "dephasing_censored": false,
          "dephasing_memory_times": 0.2,
          "tangential_fraction_median": 0.8769608045988309
        },
        "eta_zero_dynamic": {
          "angular_momentum_norm_median": 8.823550548733987e-06,
          "angular_orientation_coherence": 0.02935877856114681,
          "angular_speed_median_per_memory_time": 0.0008793391243593559,
          "dephasing_censored": false,
          "dephasing_memory_times": 1.2000000000000002,
          "tangential_fraction_median": 0.869592458757668
        },
        "free": {
          "angular_momentum_norm_median": 8.684495813173724e-07,
          "angular_orientation_coherence": 0.09762794023984565,
          "angular_speed_median_per_memory_time": 8.684362960780595e-05,
          "dephasing_censored": false,
          "dephasing_memory_times": 0.2,
          "tangential_fraction_median": 0.8763999228801882
        },
        "frozen_source": {
          "angular_momentum_norm_median": 5.869265699969316e-07,
          "angular_orientation_coherence": 0.005951923409540322,
          "angular_speed_median_per_memory_time": 5.867855310929889e-05,
          "dephasing_censored": false,
          "dephasing_memory_times": 0.2,
          "tangential_fraction_median": 0.876749568539016
        }
      },
      "source_displacement_radii": 8.673268604688797,
      "source_launch_axis": 1,
      "source_launch_sigma_rep": 0.1,
      "source_launch_start_step": 5000,
      "source_launch_steps": 1000,
      "source_shape_response": {
        "max_radius_factor": 1.5904457119683941,
        "radius_factor_limit": 2.0,
        "shape_bounded_coherent_pass": true,
        "shape_bounded_pass": true,
        "shape_coherent_pass": true,
        "shape_spectrum_distance_median": 1.5265566588595902e-15,
        "shape_spectrum_distance_q95": 0.24294164878303526,
        "spectrum_median_limit": 0.1,
        "spectrum_q95_limit": 0.25
      },
      "source_stationarity": {
        "radius_coefficient_of_variation": 0.05095841839149912,
        "radius_cv_limit": 0.15,
        "radius_drift_limit": 0.1,
        "radius_relative_drift": 0.029265263177555734,
        "shape_spectrum_total_variation": 0.006411613217479267,
        "spectrum_drift_limit": 0.1,
        "stationary_shape_pass": true
      },
      "target_shape_response": {
        "max_radius_factor": 1.0000003647309703,
        "radius_factor_limit": 2.0,
        "shape_bounded_coherent_pass": true,
        "shape_bounded_pass": true,
        "shape_coherent_pass": true,
        "shape_spectrum_distance_median": 1.1640592573192166e-07,
        "shape_spectrum_distance_q95": 2.843182224515628e-07,
        "spectrum_median_limit": 0.1,
        "spectrum_q95_limit": 0.25
      }
    },
    {
      "continuation_seed": 3,
      "dynamic_minus_free_final_radii": 0.13899697247104406,
      "dynamic_minus_frozen_final_radii": 0.0002532436348143669,
      "dynamic_separation_final": 1.0004825274487523,
      "dynamic_separation_initial": 0.9999999999999974,
      "dynamic_separation_ratio": 1.000482527448755,
      "launch_specific_source_displacement_radii": 10.94402934482225,
      "launch_specific_target_response_radii": 0.00023323640341226263,
      "max_active_target_radius_disturbance": 0.0001676806198867009,
      "max_eta_zero_radius_disturbance": 8.693303389263697,
      "max_launch_specific_source_radius_effect": 0.5655532779702295,
      "max_source_radius_disturbance": 0.544066783806626,
      "orbital_metrics": {
        "dynamic_source": {
          "angular_momentum_norm_median": 8.562434302589972e-07,
          "angular_orientation_coherence": 0.10789209559454283,
          "angular_speed_median_per_memory_time": 8.559772729986023e-05,
          "dephasing_censored": false,
          "dephasing_memory_times": 0.2,
          "tangential_fraction_median": 0.894817961649286
        },
        "eta_zero_dynamic": {
          "angular_momentum_norm_median": 8.560756622250165e-06,
          "angular_orientation_coherence": 0.07955376839293019,
          "angular_speed_median_per_memory_time": 0.0008413744292094464,
          "dephasing_censored": false,
          "dephasing_memory_times": 1.4000000000000001,
          "tangential_fraction_median": 0.8474943293319304
        },
        "free": {
          "angular_momentum_norm_median": 8.562524914963323e-07,
          "angular_orientation_coherence": 0.10789109713798711,
          "angular_speed_median_per_memory_time": 8.559739544582638e-05,
          "dephasing_censored": false,
          "dephasing_memory_times": 0.2,
          "tangential_fraction_median": 0.8947154619573369
        },
        "frozen_source": {
          "angular_momentum_norm_median": 5.812424745202242e-07,
          "angular_orientation_coherence": 0.03287257805443219,
          "angular_speed_median_per_memory_time": 5.809855313360347e-05,
          "dephasing_censored": false,
          "dephasing_memory_times": 0.2,
          "tangential_fraction_median": 0.8687380208791708
        }
      },
      "source_displacement_radii": 11.520267012421225,
      "source_launch_axis": 1,
      "source_launch_sigma_rep": 0.1,
      "source_launch_start_step": 5000,
      "source_launch_steps": 1000,
      "source_shape_response": {
        "max_radius_factor": 1.6121945758044245,
        "radius_factor_limit": 2.0,
        "shape_bounded_coherent_pass": true,
        "shape_bounded_pass": true,
        "shape_coherent_pass": true,
        "shape_spectrum_distance_median": 3.3306690738754696e-16,
        "shape_spectrum_distance_q95": 0.2150692008700611,
        "spectrum_median_limit": 0.1,
        "spectrum_q95_limit": 0.25
      },
      "source_stationarity": {
        "radius_coefficient_of_variation": 0.03860280720132554,
        "radius_cv_limit": 0.15,
        "radius_drift_limit": 0.1,
        "radius_relative_drift": 0.011133523189866157,
        "shape_spectrum_total_variation": 0.005192758758562704,
        "spectrum_drift_limit": 0.1,
        "stationary_shape_pass": true
      },
      "target_shape_response": {
        "max_radius_factor": 1.0000003540934452,
        "radius_factor_limit": 2.0,
        "shape_bounded_coherent_pass": true,
        "shape_bounded_pass": true,
        "shape_coherent_pass": true,
        "shape_spectrum_distance_median": 1.1485851711401374e-07,
        "shape_spectrum_distance_q95": 2.5807292550195093e-07,
        "spectrum_median_limit": 0.1,
        "spectrum_q95_limit": 0.25
      }
    },
    {
      "continuation_seed": 4,
      "dynamic_minus_free_final_radii": 0.13891897796637118,
      "dynamic_minus_frozen_final_radii": 0.00019228089321434295,
      "dynamic_separation_final": 0.999538975370119,
      "dynamic_separation_initial": 0.9999999999999974,
      "dynamic_separation_ratio": 0.9995389753701216,
      "launch_specific_source_displacement_radii": 10.944029310513114,
      "launch_specific_target_response_radii": 0.00023322514697177938,
      "max_active_target_radius_disturbance": 0.00015121221496328108,
      "max_eta_zero_radius_disturbance": 8.163944092907183,
      "max_launch_specific_source_radius_effect": 0.5678176534506263,
      "max_source_radius_disturbance": 0.5268959774059687,
      "orbital_metrics": {
        "dynamic_source": {
          "angular_momentum_norm_median": 8.406341849935647e-07,
          "angular_orientation_coherence": 0.05426631220038486,
          "angular_speed_median_per_memory_time": 8.406085101278844e-05,
          "dephasing_censored": false,
          "dephasing_memory_times": 0.2,
          "tangential_fraction_median": 0.874842738425918
        },
        "eta_zero_dynamic": {
          "angular_momentum_norm_median": 7.4203864145223764e-06,
          "angular_orientation_coherence": 0.1628813270327244,
          "angular_speed_median_per_memory_time": 0.0007357712193535531,
          "dephasing_censored": false,
          "dephasing_memory_times": 1.2000000000000002,
          "tangential_fraction_median": 0.817371812344857
        },
        "free": {
          "angular_momentum_norm_median": 8.406465031840059e-07,
          "angular_orientation_coherence": 0.05426535892298331,
          "angular_speed_median_per_memory_time": 8.405962404782678e-05,
          "dephasing_censored": false,
          "dephasing_memory_times": 0.2,
          "tangential_fraction_median": 0.8750426480779708
        },
        "frozen_source": {
          "angular_momentum_norm_median": 5.683310364524329e-07,
          "angular_orientation_coherence": 0.0553347538756516,
          "angular_speed_median_per_memory_time": 5.681540124952436e-05,
          "dephasing_censored": false,
          "dephasing_memory_times": 0.2,
          "tangential_fraction_median": 0.8603289132726444
        }
      },
      "source_displacement_radii": 7.809098895880205,
      "source_launch_axis": 1,
      "source_launch_sigma_rep": 0.1,
      "source_launch_start_step": 5000,
      "source_launch_steps": 1000,
      "source_shape_response": {
        "max_radius_factor": 1.5934163661952154,
        "radius_factor_limit": 2.0,
        "shape_bounded_coherent_pass": false,
        "shape_bounded_pass": true,
        "shape_coherent_pass": false,
        "shape_spectrum_distance_median": 6.661338147750939e-16,
        "shape_spectrum_distance_q95": 0.272893004581954,
        "spectrum_median_limit": 0.1,
        "spectrum_q95_limit": 0.25
      },
      "source_stationarity": {
        "radius_coefficient_of_variation": 0.04080935480508094,
        "radius_cv_limit": 0.15,
        "radius_drift_limit": 0.1,
        "radius_relative_drift": 0.0019702368728784503,
        "shape_spectrum_total_variation": 0.006319263485189575,
        "spectrum_drift_limit": 0.1,
        "stationary_shape_pass": true
      },
      "target_shape_response": {
        "max_radius_factor": 1.0000003923576957,
        "radius_factor_limit": 2.0,
        "shape_bounded_coherent_pass": true,
        "shape_bounded_pass": true,
        "shape_coherent_pass": true,
        "shape_spectrum_distance_median": 1.1103260344480503e-07,
        "shape_spectrum_distance_q95": 2.794792293911441e-07,
        "spectrum_median_limit": 0.1,
        "spectrum_q95_limit": 0.25
      }
    },
    {
      "continuation_seed": 5,
      "dynamic_minus_free_final_radii": 0.13892940667427295,
      "dynamic_minus_frozen_final_radii": 0.00022062412836418576,
      "dynamic_separation_final": 1.000344310200439,
      "dynamic_separation_initial": 0.9999999999999974,
      "dynamic_separation_ratio": 1.0003443102004417,
      "launch_specific_source_displacement_radii": 10.944029337664135,
      "launch_specific_target_response_radii": 0.00023322735875311385,
      "max_active_target_radius_disturbance": 0.00015724248296011822,
      "max_eta_zero_radius_disturbance": 9.044868450826598,
      "max_launch_specific_source_radius_effect": 0.5287620797247471,
      "max_source_radius_disturbance": 0.5047219191280343,
      "orbital_metrics": {
        "dynamic_source": {
          "angular_momentum_norm_median": 8.35043835588712e-07,
          "angular_orientation_coherence": 0.08658026017917032,
          "angular_speed_median_per_memory_time": 8.352862715410468e-05,
          "dephasing_censored": false,
          "dephasing_memory_times": 0.2,
          "tangential_fraction_median": 0.8705043330482996
        },
        "eta_zero_dynamic": {
          "angular_momentum_norm_median": 7.447285275274964e-06,
          "angular_orientation_coherence": 0.06523096792669544,
          "angular_speed_median_per_memory_time": 0.0007497492171503548,
          "dephasing_censored": false,
          "dephasing_memory_times": 1.0,
          "tangential_fraction_median": 0.8395149835579698
        },
        "free": {
          "angular_momentum_norm_median": 8.35051871192661e-07,
          "angular_orientation_coherence": 0.0865793899921471,
          "angular_speed_median_per_memory_time": 8.352783405795001e-05,
          "dephasing_censored": false,
          "dephasing_memory_times": 0.2,
          "tangential_fraction_median": 0.8703513595164782
        },
        "frozen_source": {
          "angular_momentum_norm_median": 5.722486199889993e-07,
          "angular_orientation_coherence": 0.024291955108183428,
          "angular_speed_median_per_memory_time": 5.724205059900984e-05,
          "dephasing_censored": false,
          "dephasing_memory_times": 0.2,
          "tangential_fraction_median": 0.8586047983866767
        }
      },
      "source_displacement_radii": 8.953839498370156,
      "source_launch_axis": 1,
      "source_launch_sigma_rep": 0.1,
      "source_launch_start_step": 5000,
      "source_launch_steps": 1000,
      "source_shape_response": {
        "max_radius_factor": 1.5476114270653407,
        "radius_factor_limit": 2.0,
        "shape_bounded_coherent_pass": false,
        "shape_bounded_pass": true,
        "shape_coherent_pass": false,
        "shape_spectrum_distance_median": 1.2545520178264269e-14,
        "shape_spectrum_distance_q95": 0.2522376852458329,
        "spectrum_median_limit": 0.1,
        "spectrum_q95_limit": 0.25
      },
      "source_stationarity": {
        "radius_coefficient_of_variation": 0.03154736150580174,
        "radius_cv_limit": 0.15,
        "radius_drift_limit": 0.1,
        "radius_relative_drift": 0.00715913834136328,
        "shape_spectrum_total_variation": 0.007838402274125467,
        "spectrum_drift_limit": 0.1,
        "stationary_shape_pass": true
      },
      "target_shape_response": {
        "max_radius_factor": 1.0000003471942474,
        "radius_factor_limit": 2.0,
        "shape_bounded_coherent_pass": true,
        "shape_bounded_pass": true,
        "shape_coherent_pass": true,
        "shape_spectrum_distance_median": 1.1192465546039365e-07,
        "shape_spectrum_distance_q95": 2.6325898825479976e-07,
        "spectrum_median_limit": 0.1,
        "spectrum_q95_limit": 0.25
      }
    }
  ]
}
